rumydata/__init__.py
rumydata/_base.py
rumydata/exception.py
rumydata/field.py
rumydata/menu.py
rumydata/table.py
rumydata/rules/__init__.py
rumydata/rules/cell.py
rumydata/rules/column.py
rumydata/rules/header.py
rumydata/rules/row.py
rumydata/rules/table.py
tests/__init__.py
tests/conftest.py
tests/test_exception.py
tests/test_fields.py
tests/test_menu.py
tests/test_other.py
tests/test_parquet.py
tests/test_row.py
tests/test_rules_base.py
tests/test_rules_cell.py
tests/test_rules_column.py
tests/test_rules_header.py
tests/test_table.py
tests/utils.py
rumydata-1.5.0.dist-info/LICENSE
rumydata-1.5.0.dist-info/METADATA
rumydata-1.5.0.dist-info/WHEEL
rumydata-1.5.0.dist-info/top_level.txt
rumydata-1.5.0.dist-info/RECORD
