Metadata-Version: 2.1
Name: rumydata
Version: 1.5.0
Summary: A python package for validating expectations of text data, and safely reporting exceptions
Home-page: https://github.com/Mikuana/rumydata
Author: Christopher Boyd
Classifier: Programming Language :: Python :: 3
Classifier: License :: OSI Approved :: MIT License
Classifier: Operating System :: OS Independent
Requires-Python: >=3.7
License-File: LICENSE
Provides-Extra: excel
Requires-Dist: openpyxl ; extra == 'excel'
Provides-Extra: html
Requires-Dist: markdown ; extra == 'html'
Provides-Extra: parquet
Requires-Dist: pandas ; extra == 'parquet'
Requires-Dist: pyarrow ; extra == 'parquet'
Provides-Extra: testing
Requires-Dist: pytest ; extra == 'testing'
Requires-Dist: pytest-mock ; extra == 'testing'
Requires-Dist: pytest-cov ; extra == 'testing'
Requires-Dist: openpyxl ; extra == 'testing'
Requires-Dist: markdown ; extra == 'testing'
Requires-Dist: pandas ; extra == 'testing'
Requires-Dist: pyarrow ; extra == 'testing'
